codewars_cli/__init__.py
codewars_cli-0.1.1.dist-info/entry_points.txt
codewars_cli-0.1.1.dist-info/LICENSE
codewars_cli-0.1.1.dist-info/WHEEL
codewars_cli-0.1.1.dist-info/METADATA
codewars_cli-0.1.1.dist-info/RECORD
