Metadata-Version: 2.1
Name: codewars-cli
Version: 0.1.1
Summary: An unofficial CLI for CodeWars.
Home-page: https://github.com/kappq/codewars-cli
License: MIT
Keywords: cli
Author: Kappa
Author-email: f.cappetti.05@gmail.com
Requires-Python: >=3.10,<4.0
Classifier: License :: OSI Approved :: MIT License
Classifier: Operating System :: OS Independent
Classifier: Programming Language :: Python :: 3
Classifier: Programming Language :: Python :: 3.10
Classifier: Programming Language :: Python :: 3.11
Requires-Dist: bs4 (>=0.0.1,<0.0.2)
Requires-Dist: click (>=8.1.3,<9.0.0)
Requires-Dist: cloudscraper (>=1.2.66,<2.0.0)
Requires-Dist: rich (>=12.6.0,<13.0.0)
Requires-Dist: toml (>=0.10.2,<0.11.0)
Project-URL: Repository, https://github.com/kappq/codewars-cli
